[
  {
    "id": "tip-001-warm-foods",
    "status": "published",
    "category": "digestive-herbs",
    "source": {
      "work": "Чжуд-ши",
      "part": "Тантра объяснений",
      "chapter": "гл. 14 «Сезонный образ жизни»"
    }
  },
  {
    "id": "tip-002-rhythm",
    "status": "published",
    "source": {
      "work": "Чжуд-ши",
      "part": "Тантра объяснений",
      "chapter": "гл. 13 «Повседневный образ жизни»"
    }
  },
  {
    "id": "tip-003-seasonal-eating-rhythm",
    "status": "published",
    "source": {
      "work": "Чжуд-ши",
      "part": "Тантра объяснений",
      "chapter": "гл. 14 «Сезонный образ жизни»"
    }
  },
  {
    "id": "tip-004-seasonal-food-qualities",
    "status": "published",
    "category": "digestive-herbs",
    "source": {
      "work": "Чжуд-ши",
      "part": "Тантра объяснений",
      "chapter": "гл. 14 «Сезонный образ жизни»"
    }
  },
  {
    "id": "tip-005-measure-of-eating",
    "status": "published",
    "category": "digestive-herbs",
    "source": {
      "work": "Чжуд-ши",
      "part": "Тантра объяснений",
      "chapter": "гл. 18 «Мера питания»"
    }
  },
  {
    "id": "tip-006-light-and-heavy-foods",
    "status": "published",
    "category": "digestive-herbs",
    "source": {
      "work": "Чжуд-ши",
      "part": "Тантра объяснений",
      "chapter": "гл. 16 «О том, как надо питаться»"
    }
  },
  {
    "id": "tip-007-six-tastes",
    "status": "published",
    "source": {
      "work": "Чжуд-ши",
      "part": "Тантра объяснений",
      "chapter": "гл. 19 «Вкусы»"
    }
  },
  {
    "id": "tip-008-warm-water",
    "status": "published",
    "category": "digestive-herbs",
    "source": {
      "work": "Чжуд-ши",
      "part": "Тантра объяснений",
      "chapter": "гл. 16 «О том, как надо питаться»"
    }
  },
  {
    "id": "tip-009-natural-urges",
    "status": "published",
    "source": {
      "work": "Чжуд-ши",
      "part": "Тантра объяснений",
      "chapter": "гл. 15 «Как вести себя в частных случаях»"
    }
  },
  {
    "id": "tip-010-conditions-of-illness",
    "status": "published",
    "source": {
      "work": "Чжуд-ши",
      "part": "Тантра объяснений",
      "chapter": "гл. 23 «Как жить не болея»"
    }
  },
  {
    "id": "tip-011-spring-conduct",
    "status": "published",
    "source": {
      "work": "Чжуд-ши",
      "part": "Тантра объяснений",
      "chapter": "гл. 14 «Сезонный образ жизни»"
    }
  },
  {
    "id": "tip-012-summer-conduct",
    "status": "published",
    "source": {
      "work": "Чжуд-ши",
      "part": "Тантра объяснений",
      "chapter": "гл. 14 «Сезонный образ жизни»"
    }
  },
  {
    "id": "tip-013-autumn-conduct",
    "status": "published",
    "source": {
      "work": "Чжуд-ши",
      "part": "Тантра объяснений",
      "chapter": "гл. 14 «Сезонный образ жизни»"
    }
  },
  {
    "id": "tip-014-winter-conduct",
    "status": "published",
    "source": {
      "work": "Чжуд-ши",
      "part": "Тантра объяснений",
      "chapter": "гл. 14 «Сезонный образ жизни»"
    }
  },
  {
    "id": "tip-015-body-oiling",
    "status": "published",
    "source": {
      "work": "Чжуд-ши",
      "part": "Тантра объяснений",
      "chapter": "гл. 13 «Повседневный образ жизни»"
    }
  },
  {
    "id": "tip-016-sense-organs",
    "status": "published",
    "source": {
      "work": "Чжуд-ши",
      "part": "Тантра объяснений",
      "chapter": "гл. 13 «Повседневный образ жизни»"
    }
  },
  {
    "id": "tip-017-physical-activity",
    "status": "published",
    "source": {
      "work": "Чжуд-ши",
      "part": "Тантра объяснений",
      "chapter": "гл. 13 «Повседневный образ жизни»"
    }
  },
  {
    "id": "tip-018-care-in-special-cases",
    "status": "published",
    "source": {
      "work": "Чжуд-ши",
      "part": "Тантра объяснений",
      "chapter": "гл. 15 «Как вести себя в частных случаях»"
    }
  },
  {
    "id": "tip-019-fresh-warm-food",
    "status": "published",
    "source": {
      "work": "Чжуд-ши",
      "part": "Тантра объяснений",
      "chapter": "гл. 16 «О том, как надо питаться»"
    }
  },
  {
    "id": "tip-020-digest-before-next",
    "status": "published",
    "source": {
      "work": "Чжуд-ши",
      "part": "Тантра объяснений",
      "chapter": "гл. 16 «О том, как надо питаться»"
    }
  },
  {
    "id": "tip-021-measure-by-digestion",
    "status": "published",
    "source": {
      "work": "Чжуд-ши",
      "part": "Тантра объяснений",
      "chapter": "гл. 18 «Мера питания»"
    }
  },
  {
    "id": "tip-022-sweet-taste",
    "status": "published",
    "source": {
      "work": "Чжуд-ши",
      "part": "Тантра объяснений",
      "chapter": "гл. 19 «Вкусы»"
    }
  },
  {
    "id": "tip-023-pungent-taste",
    "status": "published",
    "source": {
      "work": "Чжуд-ши",
      "part": "Тантра объяснений",
      "chapter": "гл. 19 «Вкусы»"
    }
  },
  {
    "id": "tip-024-bitter-astringent-taste",
    "status": "published",
    "source": {
      "work": "Чжуд-ши",
      "part": "Тантра объяснений",
      "chapter": "гл. 19 «Вкусы»"
    }
  },
  {
    "id": "tip-025-sour-salty-taste",
    "status": "published",
    "source": {
      "work": "Чжуд-ши",
      "part": "Тантра объяснений",
      "chapter": "гл. 19 «Вкусы»"
    }
  },
  {
    "id": "tip-026-post-digestive-taste",
    "status": "published",
    "source": {
      "work": "Чжуд-ши",
      "part": "Тантра объяснений",
      "chapter": "гл. 19 «Вкусы»"
    }
  },
  {
    "id": "tip-027-moderation-prevention",
    "status": "published",
    "source": {
      "work": "Чжуд-ши",
      "part": "Тантра объяснений",
      "chapter": "гл. 23 «Как жить не болея»"
    }
  },
  {
    "id": "tip-028-early-signs",
    "status": "published",
    "source": {
      "work": "Чжуд-ши",
      "part": "Тантра объяснений",
      "chapter": "гл. 23 «Как жить не болея»"
    }
  },
  {
    "id": "tip-029-mental-conduct",
    "status": "published",
    "source": {
      "work": "Чжуд-ши",
      "part": "Тантра объяснений",
      "chapter": "гл. 13 «Повседневный образ жизни»"
    }
  },
  {
    "id": "tip-030-not-forcing-urges",
    "status": "published",
    "source": {
      "work": "Чжуд-ши",
      "part": "Тантра объяснений",
      "chapter": "гл. 15 «Как вести себя в частных случаях»"
    }
  },
  {
    "id": "tip-031-constitution-diet-overview",
    "status": "published",
    "source": {
      "work": "Сова Ригпа",
      "part": "«Наука о здоровье» (Ринчен Тензин)",
      "chapter": "гл. 3 «Люди природы Ветра, Огня, Земли-Воды»"
    }
  },
  {
    "id": "tip-032-wind-diet",
    "status": "published",
    "source": {
      "work": "Сова Ригпа",
      "part": "«Наука о здоровье» (Ринчен Тензин)",
      "chapter": "гл. 3 «Питание при расстройствах Ветра»"
    }
  },
  {
    "id": "tip-033-bile-diet",
    "status": "published",
    "source": {
      "work": "Сова Ригпа",
      "part": "«Наука о здоровье» (Ринчен Тензин)",
      "chapter": "гл. 3 «Питание при расстройствах Огня»"
    }
  },
  {
    "id": "tip-034-phlegm-diet",
    "status": "published",
    "source": {
      "work": "Сова Ригпа",
      "part": "«Наука о здоровье» (Ринчен Тензин)",
      "chapter": "гл. 3 «Питание при расстройствах Земли-Воды»"
    }
  },
  {
    "id": "tip-035-water-drinking",
    "status": "published",
    "source": {
      "work": "Сова Ригпа",
      "part": "«Наука о здоровье» (Ринчен Тензин)",
      "chapter": "гл. 2 «О питании в целом»"
    }
  },
  {
    "id": "tip-036-incompatible-foods",
    "status": "published",
    "source": {
      "work": "Сова Ригпа",
      "chapter": "раздел «Несовместимая пища»"
    }
  },
  {
    "id": "tip-037-cooking-method",
    "status": "published",
    "source": {
      "work": "Сова Ригпа",
      "part": "«Наука о здоровье» (Ринчен Тензин)",
      "chapter": "гл. 4 «Приготовление пищи»"
    }
  },
  {
    "id": "tip-038-food-form",
    "status": "published",
    "source": {
      "work": "Сова Ригпа",
      "part": "«Наука о здоровье» (Ринчен Тензин)",
      "chapter": "гл. 4 «Приготовление пищи»"
    }
  },
  {
    "id": "tip-039-when-to-eat",
    "status": "published",
    "source": {
      "work": "Сова Ригпа",
      "part": "«Наука о здоровье» (Ринчен Тензин)",
      "chapter": "гл. 2 «О питании в целом»"
    }
  },
  {
    "id": "tip-040-quantity-naturalness",
    "status": "published",
    "source": {
      "work": "Сова Ригпа",
      "part": "«Наука о здоровье» (Ринчен Тензин)",
      "chapter": "гл. 2 «О питании в целом»"
    }
  },
  {
    "id": "tip-041-weight-and-constitution",
    "status": "published",
    "source": {
      "work": "Сова Ригпа",
      "part": "«Наука о здоровье» (Ринчен Тензин)",
      "chapter": "гл. 3 «Питание при расстройствах Земли-Воды»"
    }
  },
  {
    "id": "tip-042-fasting-tradition",
    "status": "published",
    "source": {
      "work": "Сова Ригпа",
      "chapter": "раздел «Очищение, голодание и пост»"
    }
  },
  {
    "id": "tip-043-mono-diets",
    "status": "published",
    "source": {
      "work": "Сова Ригпа",
      "chapter": "раздел «Моно-диеты»"
    }
  },
  {
    "id": "tip-044-strengthening-body",
    "status": "published",
    "source": {
      "work": "Сова Ригпа",
      "chapter": "раздел «Как укрепить тело»"
    }
  },
  {
    "id": "tip-045-healthy-habits",
    "status": "published",
    "source": {
      "work": "Сова Ригпа",
      "chapter": "раздел «Здоровые привычки»"
    }
  },
  {
    "id": "tip-046-constitution-behavior",
    "status": "published",
    "source": {
      "work": "Сова Ригпа",
      "part": "«Наука о здоровье» (Ринчен Тензин)",
      "chapter": "гл. 3 «Люди природы Ветра, Огня, Земли-Воды»"
    }
  },
  {
    "id": "tip-047-body-care-daily",
    "status": "published",
    "source": {
      "work": "Сова Ригпа",
      "part": "«Наука о здоровье» (Ринчен Тензин)",
      "chapter": "гл. 3 «Люди природы Ветра, Огня, Земли-Воды»"
    }
  },
  {
    "id": "tip-048-sleep",
    "status": "published",
    "source": {
      "work": "Сова Ригпа",
      "part": "«Наука о здоровье» (Ринчен Тензин)",
      "chapter": "гл. 2 «Питание и образ жизни»"
    }
  },
  {
    "id": "tip-049-insomnia",
    "status": "published",
    "source": {
      "work": "Сова Ригпа",
      "part": "«Наука о здоровье» (Ринчен Тензин)",
      "chapter": "гл. 3 «Образ жизни при расстройствах Ветра»"
    }
  },
  {
    "id": "tip-050-daytime-sleepiness",
    "status": "published",
    "source": {
      "work": "Сова Ригпа",
      "part": "«Наука о здоровье» (Ринчен Тензин)",
      "chapter": "гл. 3 «Образ жизни при расстройствах Земли-Воды»"
    }
  },
  {
    "id": "tip-051-cold-onset",
    "status": "published",
    "source": {
      "work": "Сова Ригпа",
      "chapter": "раздел «Как справляться с „простудой\"»"
    }
  },
  {
    "id": "tip-052-prostration-exercise",
    "status": "published",
    "source": {
      "work": "Сова Ригпа",
      "part": "«Наука о здоровье» (Ринчен Тензин)",
      "chapter": "гл. 3 «Образ жизни при расстройствах Земли-Воды»"
    }
  },
  {
    "id": "tip-053-general-nutrition",
    "status": "published",
    "source": {
      "work": "Сова Ригпа",
      "part": "«Наука о здоровье» (Ринчен Тензин)",
      "chapter": "гл. 2 «О питании в целом»"
    }
  },
  {
    "id": "tip-054-what-tradition-avoids",
    "status": "published",
    "source": {
      "work": "Сова Ригпа",
      "chapter": "раздел «Само собой разумеется»"
    }
  },
  {
    "id": "tip-055-occasional-indulgence",
    "status": "published",
    "source": {
      "work": "Сова Ригпа",
      "chapter": "раздел «Приободряющее»"
    }
  },
  {
    "id": "tip-056-activity-and-rest",
    "status": "published",
    "source": {
      "work": "Сова Ригпа",
      "part": "«Наука о здоровье» (Ринчен Тензин)",
      "chapter": "гл. 2 «О времени суток»"
    }
  },
  {
    "id": "tip-057-seasonal-behavior",
    "status": "published",
    "source": {
      "work": "Сова Ригпа",
      "part": "«Наука о здоровье» (Ринчен Тензин)",
      "chapter": "гл. 2 «Изменение жизненных начал в течение года»"
    }
  },
  {
    "id": "tip-058-sense-care-daily",
    "status": "published",
    "source": {
      "work": "Сова Ригпа",
      "chapter": "раздел «Повседневное поведение»"
    }
  },
  {
    "id": "tip-059-intimacy-and-measure",
    "status": "published",
    "source": {
      "work": "Сова Ригпа",
      "part": "«Наука о здоровье» (Ринчен Тензин)",
      "chapter": "гл. 3 «Образ жизни при расстройствах Ветра»"
    }
  },
  {
    "id": "tip-060-age-and-constitution",
    "status": "published",
    "source": {
      "work": "Сова Ригпа",
      "chapter": "раздел «Питание согласно конституции»"
    }
  },
  {
    "id": "tip-061-causes-of-illness",
    "status": "published",
    "source": {
      "work": "Чжуд-ши",
      "part": "Тантра объяснений",
      "chapter": "гл. 8 «Причины болезней»"
    }
  },
  {
    "id": "tip-062-bile-is-fire",
    "status": "published",
    "source": {
      "work": "Чжуд-ши",
      "part": "Тантра объяснений",
      "chapter": "гл. 9 «Условия возникновения болезней»"
    }
  },
  {
    "id": "tip-063-phlegm-earth-water",
    "status": "published",
    "source": {
      "work": "Чжуд-ши",
      "part": "Тантра объяснений",
      "chapter": "гл. 9 «Условия возникновения болезней»"
    }
  },
  {
    "id": "tip-064-wind-pervades",
    "status": "published",
    "source": {
      "work": "Чжуд-ши",
      "part": "Тантра объяснений",
      "chapter": "гл. 9 «Условия возникновения болезней»"
    }
  },
  {
    "id": "tip-065-doshas-in-balance",
    "status": "published",
    "source": {
      "work": "Чжуд-ши",
      "part": "Тантра объяснений",
      "chapter": "гл. 9 «Условия возникновения болезней»"
    }
  },
  {
    "id": "tip-066-conception-elements",
    "status": "published",
    "source": {
      "work": "Чжуд-ши",
      "part": "Тантра объяснений",
      "chapter": "гл. 2 «Зачатие»"
    }
  },
  {
    "id": "tip-067-body-types",
    "status": "published",
    "source": {
      "work": "Чжуд-ши",
      "part": "Тантра объяснений",
      "chapter": "гл. 6 «Деяния и типы телосложения»"
    }
  },
  {
    "id": "tip-068-body-as-tree",
    "status": "published",
    "source": {
      "work": "Чжуд-ши",
      "part": "Тантра объяснений",
      "chapter": "гл. 4 «Строение тела»"
    }
  },
  {
    "id": "tip-069-grain-properties",
    "status": "published",
    "source": {
      "work": "Чжуд-ши",
      "part": "Тантра объяснений",
      "chapter": "гл. 16 «О том, как надо питаться»"
    }
  },
  {
    "id": "tip-070-meat-properties",
    "status": "published",
    "source": {
      "work": "Чжуд-ши",
      "part": "Тантра объяснений",
      "chapter": "гл. 16 «О том, как надо питаться»"
    }
  },
  {
    "id": "tip-071-oil-for-mind",
    "status": "published",
    "source": {
      "work": "Чжуд-ши",
      "part": "Тантра объяснений",
      "chapter": "гл. 16 «О том, как надо питаться»"
    }
  },
  {
    "id": "tip-072-bathing",
    "status": "published",
    "source": {
      "work": "Чжуд-ши",
      "part": "Тантра объяснений",
      "chapter": "гл. 13 «Повседневный образ жизни»"
    }
  },
  {
    "id": "tip-073-incompatible-canon",
    "status": "published",
    "source": {
      "work": "Чжуд-ши",
      "part": "Тантра объяснений",
      "chapter": "гл. 17 «Пищевые запреты»"
    }
  },
  {
    "id": "tip-074-tradition-origins",
    "status": "published",
    "source": {
      "work": "Сова Ригпа",
      "part": "«Наука о здоровье» (Ринчен Тензин)",
      "chapter": "гл. 1 «Древняя наука Сова Ригпа и законы природы»"
    }
  },
  {
    "id": "tip-075-three-divisions",
    "status": "published",
    "source": {
      "work": "Сова Ригпа",
      "part": "«Наука о здоровье» (Ринчен Тензин)",
      "chapter": "гл. 1 «Древняя наука Сова Ригпа и законы природы»"
    }
  },
  {
    "id": "tip-076-four-methods",
    "status": "published",
    "source": {
      "work": "Сова Ригпа",
      "part": "«Наука о здоровье» (Ринчен Тензин)",
      "chapter": "гл. 1 «Древняя наука Сова Ригпа и законы природы»"
    }
  },
  {
    "id": "tip-077-first-illness",
    "status": "published",
    "source": {
      "work": "Сова Ригпа",
      "part": "«Наука о здоровье» (Ринчен Тензин)",
      "chapter": "гл. 1 «Древняя наука Сова Ригпа и законы природы»"
    }
  },
  {
    "id": "tip-078-knowledge-from-observation",
    "status": "published",
    "source": {
      "work": "Сова Ригпа",
      "part": "«Наука о здоровье» (Ринчен Тензин)",
      "chapter": "гл. 1 «Древняя наука Сова Ригпа и законы природы»"
    }
  },
  {
    "id": "tip-079-elderly-wind-age",
    "status": "published",
    "source": {
      "work": "Сова Ригпа",
      "part": "«Наука о здоровье» (Ринчен Тензин)",
      "chapter": "гл. 6 «Питание и образ жизни пожилых»"
    }
  },
  {
    "id": "tip-080-elderly-meal-rhythm",
    "status": "published",
    "source": {
      "work": "Сова Ригпа",
      "part": "«Наука о здоровье» (Ринчен Тензин)",
      "chapter": "гл. 6 «Питание и образ жизни пожилых»"
    }
  },
  {
    "id": "tip-081-elderly-early-breakfast",
    "status": "published",
    "source": {
      "work": "Сова Ригпа",
      "part": "«Наука о здоровье» (Ринчен Тензин)",
      "chapter": "гл. 6 «Питание и образ жизни пожилых»"
    }
  },
  {
    "id": "tip-082-elderly-warm-belly",
    "status": "published",
    "source": {
      "work": "Сова Ригпа",
      "part": "«Наука о здоровье» (Ринчен Тензин)",
      "chapter": "гл. 6 «Питание и образ жизни пожилых»"
    }
  },
  {
    "id": "tip-083-elderly-walk-after-dinner",
    "status": "published",
    "source": {
      "work": "Сова Ригпа",
      "part": "«Наука о здоровье» (Ринчен Тензин)",
      "chapter": "гл. 6 «Питание и образ жизни пожилых»"
    }
  },
  {
    "id": "tip-084-preheat-oil",
    "status": "published",
    "source": {
      "work": "Сова Ригпа",
      "part": "«Наука о здоровье» (Ринчен Тензин)",
      "chapter": "гл. 4 «Продукты и их свойства»"
    }
  },
  {
    "id": "tip-085-aged-grain",
    "status": "published",
    "source": {
      "work": "Сова Ригпа",
      "part": "«Наука о здоровье» (Ринчен Тензин)",
      "chapter": "гл. 4 «Продукты и их свойства»"
    }
  },
  {
    "id": "tip-086-garden-produce",
    "status": "published",
    "source": {
      "work": "Сова Ригпа",
      "part": "«Наука о здоровье» (Ринчен Тензин)",
      "chapter": "гл. 4 «Продукты и их свойства»"
    }
  },
  {
    "id": "tip-087-processed-food",
    "status": "published",
    "source": {
      "work": "Сова Ригпа",
      "part": "«Наука о здоровье» (Ринчен Тензин)",
      "chapter": "гл. 4 «Продукты и их свойства»"
    }
  },
  {
    "id": "tip-088-staging-rice",
    "status": "staging",
    "source": {
      "work": "Сова Ригпа",
      "part": "«Наука о здоровье» (Ринчен Тензин)",
      "chapter": "гл. 4 «Продукты и их свойства»"
    }
  },
  {
    "id": "tip-089-staging-millet",
    "status": "staging",
    "source": {
      "work": "Сова Ригпа",
      "part": "«Наука о здоровье» (Ринчен Тензин)",
      "chapter": "гл. 4 «Продукты и их свойства»"
    }
  },
  {
    "id": "tip-090-staging-beans-weight",
    "status": "staging",
    "source": {
      "work": "Сова Ригпа",
      "part": "«Наука о здоровье» (Ринчен Тензин)",
      "chapter": "гл. 4 «Продукты и их свойства»"
    }
  },
  {
    "id": "tip-091-staging-beans-kidney",
    "status": "staging",
    "source": {
      "work": "Сова Ригпа",
      "part": "«Наука о здоровье» (Ринчен Тензин)",
      "chapter": "гл. 4 «Продукты и их свойства»"
    }
  },
  {
    "id": "tip-092-staging-chickpea",
    "status": "staging",
    "source": {
      "work": "Сова Ригпа",
      "part": "«Наука о здоровье» (Ринчен Тензин)",
      "chapter": "гл. 4 «Продукты и их свойства»"
    }
  },
  {
    "id": "tip-093-staging-mutton-head",
    "status": "staging",
    "source": {
      "work": "Сова Ригпа",
      "part": "«Наука о здоровье» (Ринчен Тензин)",
      "chapter": "гл. 4 «Продукты и их свойства»"
    }
  },
  {
    "id": "tip-094-staging-mouse-meat",
    "status": "staging",
    "source": {
      "work": "Сова Ригпа",
      "part": "«Наука о здоровье» (Ринчен Тензин)",
      "chapter": "гл. 4 «Продукты и их свойства»"
    }
  },
  {
    "id": "tip-095-staging-fish",
    "status": "staging",
    "source": {
      "work": "Сова Ригпа",
      "part": "«Наука о здоровье» (Ринчен Тензин)",
      "chapter": "гл. 4 «Продукты и их свойства»"
    }
  },
  {
    "id": "tip-096-staging-horse-meat",
    "status": "staging",
    "source": {
      "work": "Сова Ригпа",
      "part": "«Наука о здоровье» (Ринчен Тензин)",
      "chapter": "гл. 4 «Продукты и их свойства»"
    }
  },
  {
    "id": "tip-097-staging-radish",
    "status": "staging",
    "source": {
      "work": "Сова Ригпа",
      "part": "«Наука о здоровье» (Ринчен Тензин)",
      "chapter": "гл. 4 «Продукты и их свойства»"
    }
  },
  {
    "id": "tip-098-staging-beet",
    "status": "staging",
    "source": {
      "work": "Сова Ригпа",
      "part": "«Наука о здоровье» (Ринчен Тензин)",
      "chapter": "гл. 4 «Продукты и их свойства»"
    }
  },
  {
    "id": "tip-099-staging-potato",
    "status": "staging",
    "source": {
      "work": "Сова Ригпа",
      "part": "«Наука о здоровье» (Ринчен Тензин)",
      "chapter": "гл. 4 «Продукты и их свойства»"
    }
  },
  {
    "id": "tip-100-staging-dandelion",
    "status": "staging",
    "source": {
      "work": "Сова Ригпа",
      "part": "«Наука о здоровье» (Ринчен Тензин)",
      "chapter": "гл. 4 «Продукты и их свойства»"
    }
  },
  {
    "id": "tip-101-staging-parsley",
    "status": "staging",
    "source": {
      "work": "Сова Ригпа",
      "part": "«Наука о здоровье» (Ринчен Тензин)",
      "chapter": "гл. 4 «Продукты и их свойства»"
    }
  },
  {
    "id": "tip-102-staging-cilantro",
    "status": "staging",
    "source": {
      "work": "Сова Ригпа",
      "part": "«Наука о здоровье» (Ринчен Тензин)",
      "chapter": "гл. 4 «Продукты и их свойства»"
    }
  },
  {
    "id": "tip-103-staging-garlic-onion",
    "status": "staging",
    "source": {
      "work": "Сова Ригпа",
      "part": "«Наука о здоровье» (Ринчен Тензин)",
      "chapter": "гл. 4 «Продукты и их свойства»"
    }
  },
  {
    "id": "tip-104-staging-pumpkin",
    "status": "staging",
    "source": {
      "work": "Сова Ригпа",
      "part": "«Наука о здоровье» (Ринчен Тензин)",
      "chapter": "гл. 4 «Продукты и их свойства»"
    }
  },
  {
    "id": "tip-105-staging-peach-kernel",
    "status": "staging",
    "source": {
      "work": "Сова Ригпа",
      "part": "«Наука о здоровье» (Ринчен Тензин)",
      "chapter": "гл. 4 «Продукты и их свойства»"
    }
  },
  {
    "id": "tip-106-staging-pomegranate",
    "status": "staging",
    "source": {
      "work": "Сова Ригпа",
      "part": "«Наука о здоровье» (Ринчен Тензин)",
      "chapter": "гл. 4 «Продукты и их свойства»"
    }
  },
  {
    "id": "tip-107-staging-lemon",
    "status": "staging",
    "source": {
      "work": "Сова Ригпа",
      "part": "«Наука о здоровье» (Ринчен Тензин)",
      "chapter": "гл. 4 «Продукты и их свойства»"
    }
  },
  {
    "id": "tip-108-staging-watermelon",
    "status": "staging",
    "source": {
      "work": "Сова Ригпа",
      "part": "«Наука о здоровье» (Ринчен Тензин)",
      "chapter": "гл. 4 «Продукты и их свойства»"
    }
  },
  {
    "id": "tip-109-staging-strawberry",
    "status": "staging",
    "source": {
      "work": "Сова Ригпа",
      "part": "«Наука о здоровье» (Ринчен Тензин)",
      "chapter": "гл. 4 «Продукты и их свойства»"
    }
  },
  {
    "id": "tip-110-staging-mustard-oil",
    "status": "staging",
    "source": {
      "work": "Сова Ригпа",
      "part": "«Наука о здоровье» (Ринчен Тензин)",
      "chapter": "гл. 4 «Продукты и их свойства»"
    }
  },
  {
    "id": "tip-111-staging-bone-marrow",
    "status": "staging",
    "source": {
      "work": "Сова Ригпа",
      "part": "«Наука о здоровье» (Ринчен Тензин)",
      "chapter": "гл. 4 «Продукты и их свойства»"
    }
  },
  {
    "id": "tip-112-staging-cow-milk",
    "status": "staging",
    "source": {
      "work": "Сова Ригпа",
      "part": "«Наука о здоровье» (Ринчен Тензин)",
      "chapter": "гл. 4 «Продукты и их свойства»"
    }
  },
  {
    "id": "tip-113-staging-goat-milk",
    "status": "staging",
    "source": {
      "work": "Сова Ригпа",
      "part": "«Наука о здоровье» (Ринчен Тензин)",
      "chapter": "гл. 4 «Продукты и их свойства»"
    }
  },
  {
    "id": "tip-114-staging-sheep-milk",
    "status": "staging",
    "source": {
      "work": "Сова Ригпа",
      "part": "«Наука о здоровье» (Ринчен Тензин)",
      "chapter": "гл. 4 «Продукты и их свойства»"
    }
  },
  {
    "id": "tip-115-staging-mare-milk",
    "status": "staging",
    "source": {
      "work": "Сова Ригпа",
      "part": "«Наука о здоровье» (Ринчен Тензин)",
      "chapter": "гл. 4 «Продукты и их свойства»"
    }
  },
  {
    "id": "tip-116-staging-kefir",
    "status": "staging",
    "source": {
      "work": "Сова Ригпа",
      "part": "«Наука о здоровье» (Ринчен Тензин)",
      "chapter": "гл. 4 «Продукты и их свойства»"
    }
  },
  {
    "id": "tip-117-staging-oats",
    "status": "staging",
    "source": {
      "work": "Сова Ригпа",
      "part": "«Наука о здоровье» (Ринчен Тензин)",
      "chapter": "гл. 4 «Продукты и их свойства»"
    }
  },
  {
    "id": "tip-118-staging-elderly-digestion",
    "status": "staging",
    "source": {
      "work": "Сова Ригпа",
      "part": "«Наука о здоровье» (Ринчен Тензин)",
      "chapter": "гл. 6 «Питание и образ жизни пожилых»"
    }
  },
  {
    "id": "tip-119-staging-elderly-hypertension",
    "status": "staging",
    "source": {
      "work": "Сова Ригпа",
      "part": "«Наука о здоровье» (Ринчен Тензин)",
      "chapter": "гл. 6 «Питание и образ жизни пожилых»"
    }
  },
  {
    "id": "tip-120-staging-elderly-hypotension",
    "status": "staging",
    "source": {
      "work": "Сова Ригпа",
      "part": "«Наука о здоровье» (Ринчен Тензин)",
      "chapter": "гл. 6 «Питание и образ жизни пожилых»"
    }
  },
  {
    "id": "tip-121-staging-elderly-salt",
    "status": "staging",
    "source": {
      "work": "Сова Ригпа",
      "part": "«Наука о здоровье» (Ринчен Тензин)",
      "chapter": "гл. 6 «Питание и образ жизни пожилых»"
    }
  },
  {
    "id": "tip-122-staging-elderly-rice-constipation",
    "status": "staging",
    "source": {
      "work": "Сова Ригпа",
      "part": "«Наука о здоровье» (Ринчен Тензин)",
      "chapter": "гл. 6 «Питание и образ жизни пожилых»"
    }
  },
  {
    "id": "tip-123-staging-elderly-constipation-remedy",
    "status": "staging",
    "source": {
      "work": "Сова Ригпа",
      "part": "«Наука о здоровье» (Ринчен Тензин)",
      "chapter": "гл. 6 «Питание и образ жизни пожилых»"
    }
  },
  {
    "id": "tip-124-staging-elderly-meat-choice",
    "status": "staging",
    "source": {
      "work": "Сова Ригпа",
      "part": "«Наука о здоровье» (Ринчен Тензин)",
      "chapter": "гл. 6 «Питание и образ жизни пожилых»"
    }
  },
  {
    "id": "tip-125-staging-elderly-alcohol",
    "status": "staging",
    "source": {
      "work": "Сова Ригпа",
      "part": "«Наука о здоровье» (Ринчен Тензин)",
      "chapter": "гл. 6 «Питание и образ жизни пожилых»"
    }
  },
  {
    "id": "tip-126-staging-elderly-evening",
    "status": "staging",
    "source": {
      "work": "Сова Ригпа",
      "part": "«Наука о здоровье» (Ринчен Тензин)",
      "chapter": "гл. 6 «Питание и образ жизни пожилых»"
    }
  }
]
